{"textures":{"0":"modelengine:entity/pashjndoof"},"elements":[{"name":"cube","from":[-32.28572,0.2857132,8.428572],"to":[40.14286,39.714287,8.428572],"rotation":{"angle":-22.5,"axis":"x","origin":[8.0,8.0,8.0]},"faces":{"down":{"uv":[0.0,0.0,16.0,0.0],"rotation":0,"texture":"#0","tintindex":0},"east":{"uv":[0.0,0.0,0.0,16.0],"rotation":0,"texture":"#0","tintindex":0},"north":{"uv":[0.0,4.5,16.0,9.65625],"rotation":0,"texture":"#0","tintindex":0},"south":{"uv":[16.0,4.5,0.0,9.65625],"rotation":0,"texture":"#0","tintindex":0},"up":{"uv":[0.0,0.0,16.0,0.0],"rotation":0,"texture":"#0","tintindex":0},"west":{"uv":[0.0,0.0,0.0,16.0],"rotation":0,"texture":"#0","tintindex":0}}}],"display":{"head":{"translation":[30.400019,22.400005,0.0],"rotation":[0.0,0.0,0.0],"scale":[3.7333333,3.7333333,3.7333333]}}}