{"textures":{"0":"modelengine:entity/vs_box"},"elements":[{"name":"cube","from":[8.0,8.0,4.7],"to":[12.8,8.0,11.3],"rotation":{"angle":0.0,"axis":"x","origin":[11.6,0.19999981,7.7]},"faces":{"down":{"uv":[10.0,0.0,8.0,2.75],"rotation":0,"texture":"#0","tintindex":0},"east":{"uv":[0.0,0.0,2.75,0.0],"rotation":0,"texture":"#0","tintindex":0},"north":{"uv":[0.0,0.0,2.0,0.0],"rotation":0,"texture":"#0","tintindex":0},"south":{"uv":[0.0,0.0,2.0,0.0],"rotation":0,"texture":"#0","tintindex":0},"up":{"uv":[9.25,8.25,7.25,5.5],"rotation":0,"texture":"#0","tintindex":0},"west":{"uv":[0.0,0.0,2.75,0.0],"rotation":0,"texture":"#0","tintindex":0}}}],"display":{"head":{"translation":[0.0,-6.4,0.0],"rotation":[0.0,0.0,0.0],"scale":[3.8095,3.8095,3.8095]}}}