{"textures":{"0":"modelengine:entity/ghoul1"},"elements":[{"name":"cube","from":[7.445413,6.546771,6.711932],"to":[10.385414,9.486773,9.651932],"rotation":{"angle":0.0,"axis":"x","origin":[4.505413,8.814772,6.501932]},"faces":{"down":{"uv":[6.0,6.625,5.125,7.5],"rotation":0,"texture":"#0","tintindex":0},"east":{"uv":[6.375,4.75,7.25,5.625],"rotation":0,"texture":"#0","tintindex":0},"north":{"uv":[6.375,0.0,7.25,0.875],"rotation":0,"texture":"#0","tintindex":0},"south":{"uv":[6.375,5.625,7.25,6.5],"rotation":0,"texture":"#0","tintindex":0},"up":{"uv":[7.25,7.375,6.375,6.5],"rotation":0,"texture":"#0","tintindex":0},"west":{"uv":[1.25,6.5,2.125,7.375],"rotation":0,"texture":"#0","tintindex":0}}},{"name":"cube","from":[8.495414,4.0267715,7.5519323],"to":[9.755413,6.546771,8.811933],"rotation":{"angle":0.0,"axis":"x","origin":[4.505413,8.814772,6.501932]},"faces":{"down":{"uv":[10.5,3.125,10.125,3.5],"rotation":0,"texture":"#0","tintindex":0},"east":{"uv":[4.75,9.75,5.125,10.5],"rotation":0,"texture":"#0","tintindex":0},"north":{"uv":[4.375,9.75,4.75,10.5],"rotation":0,"texture":"#0","tintindex":0},"south":{"uv":[5.125,9.75,5.5,10.5],"rotation":0,"texture":"#0","tintindex":0},"up":{"uv":[10.5,3.125,10.125,2.75],"rotation":0,"texture":"#0","tintindex":0},"west":{"uv":[9.75,7.5,10.125,8.25],"rotation":0,"texture":"#0","tintindex":0}}}],"display":{"head":{"translation":[0.0,-6.4,0.0],"rotation":[0.0,0.0,0.0],"scale":[3.8095,3.8095,3.8095]}}}